{
  "category": "sports",
  "url": "https://www.chinatimes.com/realtimenews/20200213000615-260111",
  "title": "<h1 class=\"article-title\">殷仔水手春訓 拚再起</h1>",
  "date": "2020-02-13 04:10",
  "text": "<p>今天是西雅圖水手隊春訓投捕手報到日，簽下小聯盟合約、獲邀參加大聯盟春訓的陳偉殷，昨日開了6小時的車抵達春訓基地，並在臉書PO文表示，即使只有1％上大聯盟爭取第5號先發的機會，他也不會放棄，可見其破釜沉舟的決心非常堅定。</p><p></p><p>小聯盟約 爭取開季名單</p><p></p><p>陳偉殷昨日臉書粉絲專頁PO文如後：「明天就是春訓報到日，非常感謝水手隊給了我這次的機會，我會好好把握，並全力以赴地去爭取跟去競爭任何的可能性，就算只有1％的機會我也不會放棄的！」</p><p></p><p>陳偉殷原本與馬林魚隊簽下5年8000萬美元的合約，期限是2016-20年，今年還有最後1年2200萬美元薪資未走完，但馬林魚決定認賠殺出，去年底將他指定轉讓（DFA）。後來殷仔輾轉與水手隊在今年1月底簽下小聯盟合約，如果春訓表現佳，如願升上大聯盟，水手只要付基本薪資約60萬美元，其他仍由馬林魚付清。</p><p></p><p>陳偉殷今年春訓的目標很明確，就是力拚開季26人名單和第5號先發輪值。去年他在馬林魚出賽45場都是後援，戰績0勝1敗3中繼、自責分率6.59，是大聯盟生涯首次整季未能先發。</p><p></p><p>先發輪值 競爭者多年輕</p><p></p><p>ESPN日前預測34歲的陳偉殷有機會爭取到水手隊第5號先發投手的位置，理由是水手隊處於重整階段，需要老經驗的投手留在先發輪值。不過殷仔的競爭對手年輕力壯，包括25歲以下的馬格維修斯、柯特斯、鄧恩，還有不到30歲的瓦爾德茲等人，殷仔的壓力確實不小。</p><p></p><p>此外，今年共有7位台將參加大聯盟春訓，江少慶、黃暐傑昨分別向老虎、遊騎兵隊報到，今天是陳偉殷、胡智為（教士）、朱立人（印地安人），而紅襪隊林子偉、印地安人隊張育成則都是17日報到。</p><p>(中國時報)</p>"
}