{
  "category": "star",
  "url": "https://www.chinatimes.com/realtimenews/20200214000753-260112",
  "title": "<h1 class=\"article-title\">李宗霖遇疫情停工橫店報平安</h1>",
  "date": "2020-02-14 04:10",
  "text": "<p>新生代演員李宗霖正在新冠肺炎疫區之一的浙江省拍戲，家人朋友都很替他擔心，想說服他回台，他13日報平安：「大家放心，我很好。」他去年底拍攝導演張之亮的電影《阿麥從軍》，殺青後立刻轉往橫店投入新劇，農曆年也沒辦法和家人一起過，「這是第2年沒在家裡過年，去年錄製《青春有你》在河北過年，今年就和劇組300多人待在橫店。」</p><p></p><p>農曆年前李宗霖在橫店收到劇組停工消息，所有演職員都留在原地待命，由劇組負責一日三餐與日用品採購，住宿酒店也嚴格執行人員隔離管制，其實相對安全，李宗霖樂觀說：「劇組對我們照顧無微不至，拍戲過程中也經常會有各種需要共患難的情境產生，不要太緊張、太焦慮，就把這些日子當成是獲得不能出門的假期調養生息。」他有空就在房內做棒式變形運動健身及打發時間。</p><p></p><p>李宗霖參與錄製最新一集播出的網路綜藝節目《花花萬物》，製作單位要求他多帶些有故事、好用的物件到現場分享。平常就是科技宅男的李宗霖，帶了會自走的行李箱、免清洗豆漿機、5秒充電電蚊拍、電熱衛生衣褲等，新奇實用的物品琳琅滿目，被封為「帶貨小李」。</p><p>(中國時報)</p>"
}