{
  "category": "sports",
  "url": "https://www.chinatimes.com/realtimenews/20200211001515-260403",
  "title": "<h1 class=\"article-title\">NBA》侮辱布萊恩？這幅壁畫醜哭</h1>",
  "date": "2020-02-11 10:19",
  "text": "<p>為悼念籃壇傳奇布萊恩(Kobe Bryant)，美國印地安那州一間加油站的牆面畫上布萊恩的肖像。可惜由於畫工拙劣，引來附近球迷不滿，在網路上傳開引發議論。最後肖像被加油站抹去。</p><p></p><p></p><p></p><p>這幅肖像的人物臉部變形，但還看得出是布萊恩，球迷大罵「我的天哪，看看那張臉。那個腋毛是怎樣？太誇張了。」還說這根本是對布萊恩的二度殘害。「這不是要紀念而是要嘲弄布萊恩吧。」</p><p></p><p></p><p></p><p>不過球迷這麼說未免太刻薄，畢竟作畫的人沒有留名，可能是自願幫忙的素人畫家。更何況名人肖像、雕像做醜也很常見，何必非要逼人整幅抹掉。湖人隊官方預計為布萊恩在湖人主場史坦普中心外建一座雕像，讓球迷有更好的地方可以悼念。</p><p></p><p>(中時電子報)</p>"
}