{
  "category": "sports",
  "url": "https://www.chinatimes.com/realtimenews/20200211004184-260403",
  "title": "<h1 class=\"article-title\">疫情影響 台電男足戰蒙古延至4月</h1>",
  "date": "2020-02-11 17:58",
  "text": "<p>受新型冠狀病毒肺炎影響，原定5日出征亞足聯盃資格賽的高市台電男足，因為蒙古政府邊境管制措施而無法啟程。亞足聯（AFC）今天通知中華足協，表示台電與烏蘭巴托FC的主客兩回合資格賽，將延至4月7、14日進行，整個亞足聯盃小組賽的賽程也都全部延後，我國聯賽冠軍隊北市大同也受影響。</p><p></p><p></p><p></p><p>台電vs.烏蘭巴托FC的兩回合比賽，仍於蒙古主場先踢，至於台電主場原本排在台北田徑場，目前補賽場地尚未決定，亞足聯請足協於本月底前提報審核。系列賽勝方還要在附加賽迎戰香港超級聯賽的傑志體育會，競爭最後1張晉級東亞區小組賽門票，比賽日期則是4月21、28日。</p><p></p><p></p><p></p><p>台電是去年台灣企業甲級聯賽亞軍，冠軍大同直接進入東亞區小組賽，因為資格賽賽程延後，小組賽時間也得調整。大同在亞足聯盃小組賽有3場主場比賽，分別是5月13日迎戰港超聯冠軍和富大埔，27日遭遇晉級賽出線隊伍，6月17日對決澳門鄒北記體育會。</p><p>(中時 )</p>"
}